{
  "schemaVersion": "modelview-public-reflectivity-ptype-v1",
  "legendName": "1 km AGL reflectivity with precipitation type",
  "units": "dBZ",
  "provenance": "First-party generic precipitation-type reflectivity palette generated by scripts/generate-public-color-maps.js.",
  "rangeConvention": "[minDbzInclusive, maxDbzExclusive); maxDbzExclusive=null means the highest/open-ended bin.",
  "importantNotes": [
    "Rain, freezing rain, and sleet use a 10 dBZ filter.",
    "Snow uses a 5 dBZ filter.",
    "The leading box for each precipitation type is transparent for values below its filter threshold."
  ],
  "precipTypes": {
    "rain": {
      "displayName": "Rain",
      "filterDbz": 10,
      "visibleTickLabelsDbz": [10, 20, 30, 40, 50],
      "bins": [
        {
          "binIndex": 0,
          "label": "< 10 dBZ",
          "minDbzInclusive": null,
          "maxDbzExclusive": 10,
          "startDbz": null,
          "belowFilter": true,
          "webColor": {
            "hex": "#000000",
            "rgb": [0, 0, 0],
            "alpha": 0,
            "cssRgba": "rgba(0, 0, 0, 0.000)"
          }
        },
        {
          "binIndex": 1,
          "label": "10-12.5 dBZ",
          "minDbzInclusive": 10,
          "maxDbzExclusive": 12.5,
          "startDbz": 10,
          "belowFilter": false,
          "webColor": {
            "hex": "#37B65B",
            "rgb": [55, 182, 91],
            "alpha": 0.24,
            "cssRgba": "rgba(55, 182, 91, 0.240)"
          }
        },
        {
          "binIndex": 2,
          "label": "12.5-15 dBZ",
          "minDbzInclusive": 12.5,
          "maxDbzExclusive": 15,
          "startDbz": 12.5,
          "belowFilter": false,
          "webColor": {
            "hex": "#2EA953",
            "rgb": [46, 169, 83],
            "alpha": 0.285,
            "cssRgba": "rgba(46, 169, 83, 0.285)"
          }
        },
        {
          "binIndex": 3,
          "label": "15-17.5 dBZ",
          "minDbzInclusive": 15,
          "maxDbzExclusive": 17.5,
          "startDbz": 15,
          "belowFilter": false,
          "webColor": {
            "hex": "#269B4B",
            "rgb": [38, 155, 75],
            "alpha": 0.33,
            "cssRgba": "rgba(38, 155, 75, 0.330)"
          }
        },
        {
          "binIndex": 4,
          "label": "17.5-20 dBZ",
          "minDbzInclusive": 17.5,
          "maxDbzExclusive": 20,
          "startDbz": 17.5,
          "belowFilter": false,
          "webColor": {
            "hex": "#1D8E43",
            "rgb": [29, 142, 67],
            "alpha": 0.375,
            "cssRgba": "rgba(29, 142, 67, 0.375)"
          }
        },
        {
          "binIndex": 5,
          "label": "20-22.5 dBZ",
          "minDbzInclusive": 20,
          "maxDbzExclusive": 22.5,
          "startDbz": 20,
          "belowFilter": false,
          "webColor": {
            "hex": "#14803B",
            "rgb": [20, 128, 59],
            "alpha": 0.42,
            "cssRgba": "rgba(20, 128, 59, 0.420)"
          }
        },
        {
          "binIndex": 6,
          "label": "22.5-25 dBZ",
          "minDbzInclusive": 22.5,
          "maxDbzExclusive": 25,
          "startDbz": 22.5,
          "belowFilter": false,
          "webColor": {
            "hex": "#47913F",
            "rgb": [71, 145, 63],
            "alpha": 0.465,
            "cssRgba": "rgba(71, 145, 63, 0.465)"
          }
        },
        {
          "binIndex": 7,
          "label": "25-27.5 dBZ",
          "minDbzInclusive": 25,
          "maxDbzExclusive": 27.5,
          "startDbz": 25,
          "belowFilter": false,
          "webColor": {
            "hex": "#7AA242",
            "rgb": [122, 162, 66],
            "alpha": 0.51,
            "cssRgba": "rgba(122, 162, 66, 0.510)"
          }
        },
        {
          "binIndex": 8,
          "label": "27.5-30 dBZ",
          "minDbzInclusive": 27.5,
          "maxDbzExclusive": 30,
          "startDbz": 27.5,
          "belowFilter": false,
          "webColor": {
            "hex": "#ADB346",
            "rgb": [173, 179, 70],
            "alpha": 0.555,
            "cssRgba": "rgba(173, 179, 70, 0.555)"
          }
        },
        {
          "binIndex": 9,
          "label": "30-32.5 dBZ",
          "minDbzInclusive": 30,
          "maxDbzExclusive": 32.5,
          "startDbz": 30,
          "belowFilter": false,
          "webColor": {
            "hex": "#E0C449",
            "rgb": [224, 196, 73],
            "alpha": 0.6,
            "cssRgba": "rgba(224, 196, 73, 0.600)"
          }
        },
        {
          "binIndex": 10,
          "label": "32.5-35 dBZ",
          "minDbzInclusive": 32.5,
          "maxDbzExclusive": 35,
          "startDbz": 32.5,
          "belowFilter": false,
          "webColor": {
            "hex": "#DEAA47",
            "rgb": [222, 170, 71],
            "alpha": 0.645,
            "cssRgba": "rgba(222, 170, 71, 0.645)"
          }
        },
        {
          "binIndex": 11,
          "label": "35-37.5 dBZ",
          "minDbzInclusive": 35,
          "maxDbzExclusive": 37.5,
          "startDbz": 35,
          "belowFilter": false,
          "webColor": {
            "hex": "#DC8F46",
            "rgb": [220, 143, 70],
            "alpha": 0.69,
            "cssRgba": "rgba(220, 143, 70, 0.690)"
          }
        },
        {
          "binIndex": 12,
          "label": "37.5-40 dBZ",
          "minDbzInclusive": 37.5,
          "maxDbzExclusive": 40,
          "startDbz": 37.5,
          "belowFilter": false,
          "webColor": {
            "hex": "#DA7544",
            "rgb": [218, 117, 68],
            "alpha": 0.735,
            "cssRgba": "rgba(218, 117, 68, 0.735)"
          }
        },
        {
          "binIndex": 13,
          "label": "40-42.5 dBZ",
          "minDbzInclusive": 40,
          "maxDbzExclusive": 42.5,
          "startDbz": 40,
          "belowFilter": false,
          "webColor": {
            "hex": "#D85A42",
            "rgb": [216, 90, 66],
            "alpha": 0.78,
            "cssRgba": "rgba(216, 90, 66, 0.780)"
          }
        },
        {
          "binIndex": 14,
          "label": "42.5-45 dBZ",
          "minDbzInclusive": 42.5,
          "maxDbzExclusive": 45,
          "startDbz": 42.5,
          "belowFilter": false,
          "webColor": {
            "hex": "#C95359",
            "rgb": [201, 83, 89],
            "alpha": 0.825,
            "cssRgba": "rgba(201, 83, 89, 0.825)"
          }
        },
        {
          "binIndex": 15,
          "label": "45-47.5 dBZ",
          "minDbzInclusive": 45,
          "maxDbzExclusive": 47.5,
          "startDbz": 45,
          "belowFilter": false,
          "webColor": {
            "hex": "#BA4C70",
            "rgb": [186, 76, 112],
            "alpha": 0.87,
            "cssRgba": "rgba(186, 76, 112, 0.870)"
          }
        },
        {
          "binIndex": 16,
          "label": "47.5-50 dBZ",
          "minDbzInclusive": 47.5,
          "maxDbzExclusive": 50,
          "startDbz": 47.5,
          "belowFilter": false,
          "webColor": {
            "hex": "#AB4587",
            "rgb": [171, 69, 135],
            "alpha": 0.915,
            "cssRgba": "rgba(171, 69, 135, 0.915)"
          }
        },
        {
          "binIndex": 17,
          "label": "50-52.5 dBZ",
          "minDbzInclusive": 50,
          "maxDbzExclusive": 52.5,
          "startDbz": 50,
          "belowFilter": false,
          "webColor": {
            "hex": "#9C3E9E",
            "rgb": [156, 62, 158],
            "alpha": 0.96,
            "cssRgba": "rgba(156, 62, 158, 0.960)"
          }
        },
        {
          "binIndex": 18,
          "label": "52.5-55 dBZ",
          "minDbzInclusive": 52.5,
          "maxDbzExclusive": 55,
          "startDbz": 52.5,
          "belowFilter": false,
          "webColor": {
            "hex": "#A64FA7",
            "rgb": [166, 79, 167],
            "alpha": 1,
            "cssRgba": "rgba(166, 79, 167, 1.000)"
          }
        },
        {
          "binIndex": 19,
          "label": "55-57.5 dBZ",
          "minDbzInclusive": 55,
          "maxDbzExclusive": 57.5,
          "startDbz": 55,
          "belowFilter": false,
          "webColor": {
            "hex": "#AF60B0",
            "rgb": [175, 96, 176],
            "alpha": 1,
            "cssRgba": "rgba(175, 96, 176, 1.000)"
          }
        },
        {
          "binIndex": 20,
          "label": "57.5-60 dBZ",
          "minDbzInclusive": 57.5,
          "maxDbzExclusive": 60,
          "startDbz": 57.5,
          "belowFilter": false,
          "webColor": {
            "hex": "#B971B9",
            "rgb": [185, 113, 185],
            "alpha": 1,
            "cssRgba": "rgba(185, 113, 185, 1.000)"
          }
        },
        {
          "binIndex": 21,
          "label": "60-62.5 dBZ",
          "minDbzInclusive": 60,
          "maxDbzExclusive": 62.5,
          "startDbz": 60,
          "belowFilter": false,
          "webColor": {
            "hex": "#C282C2",
            "rgb": [194, 130, 194],
            "alpha": 1,
            "cssRgba": "rgba(194, 130, 194, 1.000)"
          }
        },
        {
          "binIndex": 22,
          "label": "62.5-65 dBZ",
          "minDbzInclusive": 62.5,
          "maxDbzExclusive": 65,
          "startDbz": 62.5,
          "belowFilter": false,
          "webColor": {
            "hex": "#CC92CC",
            "rgb": [204, 146, 204],
            "alpha": 1,
            "cssRgba": "rgba(204, 146, 204, 1.000)"
          }
        },
        {
          "binIndex": 23,
          "label": "65-67.5 dBZ",
          "minDbzInclusive": 65,
          "maxDbzExclusive": 67.5,
          "startDbz": 65,
          "belowFilter": false,
          "webColor": {
            "hex": "#D5A3D5",
            "rgb": [213, 163, 213],
            "alpha": 1,
            "cssRgba": "rgba(213, 163, 213, 1.000)"
          }
        },
        {
          "binIndex": 24,
          "label": "67.5-70 dBZ",
          "minDbzInclusive": 67.5,
          "maxDbzExclusive": 70,
          "startDbz": 67.5,
          "belowFilter": false,
          "webColor": {
            "hex": "#DFB4DE",
            "rgb": [223, 180, 222],
            "alpha": 1,
            "cssRgba": "rgba(223, 180, 222, 1.000)"
          }
        },
        {
          "binIndex": 25,
          "label": "70+ dBZ",
          "minDbzInclusive": 70,
          "maxDbzExclusive": null,
          "startDbz": 70,
          "belowFilter": false,
          "webColor": {
            "hex": "#E8C5E7",
            "rgb": [232, 197, 231],
            "alpha": 1,
            "cssRgba": "rgba(232, 197, 231, 1.000)"
          }
        }
      ]
    },
    "snow": {
      "displayName": "Snow",
      "filterDbz": 5,
      "visibleTickLabelsDbz": [5, 20, 30, 40, 50],
      "bins": [
        {
          "binIndex": 0,
          "label": "< 5 dBZ",
          "minDbzInclusive": null,
          "maxDbzExclusive": 5,
          "startDbz": null,
          "belowFilter": true,
          "webColor": {
            "hex": "#000000",
            "rgb": [0, 0, 0],
            "alpha": 0,
            "cssRgba": "rgba(0, 0, 0, 0.000)"
          }
        },
        {
          "binIndex": 1,
          "label": "5-8.8 dBZ",
          "minDbzInclusive": 5,
          "maxDbzExclusive": 8.75,
          "startDbz": 5,
          "belowFilter": false,
          "webColor": {
            "hex": "#6CC7E0",
            "rgb": [108, 199, 224],
            "alpha": 0.24,
            "cssRgba": "rgba(108, 199, 224, 0.240)"
          }
        },
        {
          "binIndex": 2,
          "label": "8.8-12.5 dBZ",
          "minDbzInclusive": 8.75,
          "maxDbzExclusive": 12.5,
          "startDbz": 8.75,
          "belowFilter": false,
          "webColor": {
            "hex": "#5FB5DB",
            "rgb": [95, 181, 219],
            "alpha": 0.285,
            "cssRgba": "rgba(95, 181, 219, 0.285)"
          }
        },
        {
          "binIndex": 3,
          "label": "12.5-16.3 dBZ",
          "minDbzInclusive": 12.5,
          "maxDbzExclusive": 16.25,
          "startDbz": 12.5,
          "belowFilter": false,
          "webColor": {
            "hex": "#53A3D5",
            "rgb": [83, 163, 213],
            "alpha": 0.33,
            "cssRgba": "rgba(83, 163, 213, 0.330)"
          }
        },
        {
          "binIndex": 4,
          "label": "16.3-20 dBZ",
          "minDbzInclusive": 16.25,
          "maxDbzExclusive": 20,
          "startDbz": 16.25,
          "belowFilter": false,
          "webColor": {
            "hex": "#4691D0",
            "rgb": [70, 145, 208],
            "alpha": 0.375,
            "cssRgba": "rgba(70, 145, 208, 0.375)"
          }
        },
        {
          "binIndex": 5,
          "label": "20-22.5 dBZ",
          "minDbzInclusive": 20,
          "maxDbzExclusive": 22.5,
          "startDbz": 20,
          "belowFilter": false,
          "webColor": {
            "hex": "#397FCA",
            "rgb": [57, 127, 202],
            "alpha": 0.42,
            "cssRgba": "rgba(57, 127, 202, 0.420)"
          }
        },
        {
          "binIndex": 6,
          "label": "22.5-25 dBZ",
          "minDbzInclusive": 22.5,
          "maxDbzExclusive": 25,
          "startDbz": 22.5,
          "belowFilter": false,
          "webColor": {
            "hex": "#4675C6",
            "rgb": [70, 117, 198],
            "alpha": 0.465,
            "cssRgba": "rgba(70, 117, 198, 0.465)"
          }
        },
        {
          "binIndex": 7,
          "label": "25-27.5 dBZ",
          "minDbzInclusive": 25,
          "maxDbzExclusive": 27.5,
          "startDbz": 25,
          "belowFilter": false,
          "webColor": {
            "hex": "#526CC1",
            "rgb": [82, 108, 193],
            "alpha": 0.51,
            "cssRgba": "rgba(82, 108, 193, 0.510)"
          }
        },
        {
          "binIndex": 8,
          "label": "27.5-30 dBZ",
          "minDbzInclusive": 27.5,
          "maxDbzExclusive": 30,
          "startDbz": 27.5,
          "belowFilter": false,
          "webColor": {
            "hex": "#5F62BD",
            "rgb": [95, 98, 189],
            "alpha": 0.555,
            "cssRgba": "rgba(95, 98, 189, 0.555)"
          }
        },
        {
          "binIndex": 9,
          "label": "30-32.5 dBZ",
          "minDbzInclusive": 30,
          "maxDbzExclusive": 32.5,
          "startDbz": 30,
          "belowFilter": false,
          "webColor": {
            "hex": "#6B58B8",
            "rgb": [107, 88, 184],
            "alpha": 0.6,
            "cssRgba": "rgba(107, 88, 184, 0.600)"
          }
        },
        {
          "binIndex": 10,
          "label": "32.5-35 dBZ",
          "minDbzInclusive": 32.5,
          "maxDbzExclusive": 35,
          "startDbz": 32.5,
          "belowFilter": false,
          "webColor": {
            "hex": "#7E59B5",
            "rgb": [126, 89, 181],
            "alpha": 0.645,
            "cssRgba": "rgba(126, 89, 181, 0.645)"
          }
        },
        {
          "binIndex": 11,
          "label": "35-37.5 dBZ",
          "minDbzInclusive": 35,
          "maxDbzExclusive": 37.5,
          "startDbz": 35,
          "belowFilter": false,
          "webColor": {
            "hex": "#915BB1",
            "rgb": [145, 91, 177],
            "alpha": 0.69,
            "cssRgba": "rgba(145, 91, 177, 0.690)"
          }
        },
        {
          "binIndex": 12,
          "label": "37.5-40 dBZ",
          "minDbzInclusive": 37.5,
          "maxDbzExclusive": 40,
          "startDbz": 37.5,
          "belowFilter": false,
          "webColor": {
            "hex": "#A35CAE",
            "rgb": [163, 92, 174],
            "alpha": 0.735,
            "cssRgba": "rgba(163, 92, 174, 0.735)"
          }
        },
        {
          "binIndex": 13,
          "label": "40-42.5 dBZ",
          "minDbzInclusive": 40,
          "maxDbzExclusive": 42.5,
          "startDbz": 40,
          "belowFilter": false,
          "webColor": {
            "hex": "#B65DAA",
            "rgb": [182, 93, 170],
            "alpha": 0.78,
            "cssRgba": "rgba(182, 93, 170, 0.780)"
          }
        },
        {
          "binIndex": 14,
          "label": "42.5-45 dBZ",
          "minDbzInclusive": 42.5,
          "maxDbzExclusive": 45,
          "startDbz": 42.5,
          "belowFilter": false,
          "webColor": {
            "hex": "#BF6BB1",
            "rgb": [191, 107, 177],
            "alpha": 0.825,
            "cssRgba": "rgba(191, 107, 177, 0.825)"
          }
        },
        {
          "binIndex": 15,
          "label": "45-47.5 dBZ",
          "minDbzInclusive": 45,
          "maxDbzExclusive": 47.5,
          "startDbz": 45,
          "belowFilter": false,
          "webColor": {
            "hex": "#C878B8",
            "rgb": [200, 120, 184],
            "alpha": 0.87,
            "cssRgba": "rgba(200, 120, 184, 0.870)"
          }
        },
        {
          "binIndex": 16,
          "label": "47.5-50 dBZ",
          "minDbzInclusive": 47.5,
          "maxDbzExclusive": 50,
          "startDbz": 47.5,
          "belowFilter": false,
          "webColor": {
            "hex": "#D086BE",
            "rgb": [208, 134, 190],
            "alpha": 0.915,
            "cssRgba": "rgba(208, 134, 190, 0.915)"
          }
        },
        {
          "binIndex": 17,
          "label": "50-52.5 dBZ",
          "minDbzInclusive": 50,
          "maxDbzExclusive": 52.5,
          "startDbz": 50,
          "belowFilter": false,
          "webColor": {
            "hex": "#D993C5",
            "rgb": [217, 147, 197],
            "alpha": 0.96,
            "cssRgba": "rgba(217, 147, 197, 0.960)"
          }
        },
        {
          "binIndex": 18,
          "label": "52.5-55 dBZ",
          "minDbzInclusive": 52.5,
          "maxDbzExclusive": 55,
          "startDbz": 52.5,
          "belowFilter": false,
          "webColor": {
            "hex": "#DC9CCA",
            "rgb": [220, 156, 202],
            "alpha": 1,
            "cssRgba": "rgba(220, 156, 202, 1.000)"
          }
        },
        {
          "binIndex": 19,
          "label": "55-57.5 dBZ",
          "minDbzInclusive": 55,
          "maxDbzExclusive": 57.5,
          "startDbz": 55,
          "belowFilter": false,
          "webColor": {
            "hex": "#DFA4CF",
            "rgb": [223, 164, 207],
            "alpha": 1,
            "cssRgba": "rgba(223, 164, 207, 1.000)"
          }
        },
        {
          "binIndex": 20,
          "label": "57.5-60 dBZ",
          "minDbzInclusive": 57.5,
          "maxDbzExclusive": 60,
          "startDbz": 57.5,
          "belowFilter": false,
          "webColor": {
            "hex": "#E1ADD3",
            "rgb": [225, 173, 211],
            "alpha": 1,
            "cssRgba": "rgba(225, 173, 211, 1.000)"
          }
        },
        {
          "binIndex": 21,
          "label": "60-62.5 dBZ",
          "minDbzInclusive": 60,
          "maxDbzExclusive": 62.5,
          "startDbz": 60,
          "belowFilter": false,
          "webColor": {
            "hex": "#E4B6D8",
            "rgb": [228, 182, 216],
            "alpha": 1,
            "cssRgba": "rgba(228, 182, 216, 1.000)"
          }
        },
        {
          "binIndex": 22,
          "label": "62.5-65 dBZ",
          "minDbzInclusive": 62.5,
          "maxDbzExclusive": 65,
          "startDbz": 62.5,
          "belowFilter": false,
          "webColor": {
            "hex": "#E7BEDD",
            "rgb": [231, 190, 221],
            "alpha": 1,
            "cssRgba": "rgba(231, 190, 221, 1.000)"
          }
        },
        {
          "binIndex": 23,
          "label": "65-67.5 dBZ",
          "minDbzInclusive": 65,
          "maxDbzExclusive": 67.5,
          "startDbz": 65,
          "belowFilter": false,
          "webColor": {
            "hex": "#EAC7E2",
            "rgb": [234, 199, 226],
            "alpha": 1,
            "cssRgba": "rgba(234, 199, 226, 1.000)"
          }
        },
        {
          "binIndex": 24,
          "label": "67.5-70 dBZ",
          "minDbzInclusive": 67.5,
          "maxDbzExclusive": 70,
          "startDbz": 67.5,
          "belowFilter": false,
          "webColor": {
            "hex": "#ECD0E6",
            "rgb": [236, 208, 230],
            "alpha": 1,
            "cssRgba": "rgba(236, 208, 230, 1.000)"
          }
        },
        {
          "binIndex": 25,
          "label": "70+ dBZ",
          "minDbzInclusive": 70,
          "maxDbzExclusive": null,
          "startDbz": 70,
          "belowFilter": false,
          "webColor": {
            "hex": "#EFD8EB",
            "rgb": [239, 216, 235],
            "alpha": 1,
            "cssRgba": "rgba(239, 216, 235, 1.000)"
          }
        }
      ]
    },
    "freezing_rain": {
      "displayName": "Freezing Rain",
      "filterDbz": 10,
      "visibleTickLabelsDbz": [10, 20, 30, 40, 50],
      "bins": [
        {
          "binIndex": 0,
          "label": "< 10 dBZ",
          "minDbzInclusive": null,
          "maxDbzExclusive": 10,
          "startDbz": null,
          "belowFilter": true,
          "webColor": {
            "hex": "#000000",
            "rgb": [0, 0, 0],
            "alpha": 0,
            "cssRgba": "rgba(0, 0, 0, 0.000)"
          }
        },
        {
          "binIndex": 1,
          "label": "10-12.5 dBZ",
          "minDbzInclusive": 10,
          "maxDbzExclusive": 12.5,
          "startDbz": 10,
          "belowFilter": false,
          "webColor": {
            "hex": "#E26DB4",
            "rgb": [226, 109, 180],
            "alpha": 0.24,
            "cssRgba": "rgba(226, 109, 180, 0.240)"
          }
        },
        {
          "binIndex": 2,
          "label": "12.5-15 dBZ",
          "minDbzInclusive": 12.5,
          "maxDbzExclusive": 15,
          "startDbz": 12.5,
          "belowFilter": false,
          "webColor": {
            "hex": "#DB61AC",
            "rgb": [219, 97, 172],
            "alpha": 0.285,
            "cssRgba": "rgba(219, 97, 172, 0.285)"
          }
        },
        {
          "binIndex": 3,
          "label": "15-17.5 dBZ",
          "minDbzInclusive": 15,
          "maxDbzExclusive": 17.5,
          "startDbz": 15,
          "belowFilter": false,
          "webColor": {
            "hex": "#D455A4",
            "rgb": [212, 85, 164],
            "alpha": 0.33,
            "cssRgba": "rgba(212, 85, 164, 0.330)"
          }
        },
        {
          "binIndex": 4,
          "label": "17.5-20 dBZ",
          "minDbzInclusive": 17.5,
          "maxDbzExclusive": 20,
          "startDbz": 17.5,
          "belowFilter": false,
          "webColor": {
            "hex": "#CC499B",
            "rgb": [204, 73, 155],
            "alpha": 0.375,
            "cssRgba": "rgba(204, 73, 155, 0.375)"
          }
        },
        {
          "binIndex": 5,
          "label": "20-22.5 dBZ",
          "minDbzInclusive": 20,
          "maxDbzExclusive": 22.5,
          "startDbz": 20,
          "belowFilter": false,
          "webColor": {
            "hex": "#C53D93",
            "rgb": [197, 61, 147],
            "alpha": 0.42,
            "cssRgba": "rgba(197, 61, 147, 0.420)"
          }
        },
        {
          "binIndex": 6,
          "label": "22.5-25 dBZ",
          "minDbzInclusive": 22.5,
          "maxDbzExclusive": 25,
          "startDbz": 22.5,
          "belowFilter": false,
          "webColor": {
            "hex": "#B93C8F",
            "rgb": [185, 60, 143],
            "alpha": 0.465,
            "cssRgba": "rgba(185, 60, 143, 0.465)"
          }
        },
        {
          "binIndex": 7,
          "label": "25-27.5 dBZ",
          "minDbzInclusive": 25,
          "maxDbzExclusive": 27.5,
          "startDbz": 25,
          "belowFilter": false,
          "webColor": {
            "hex": "#AD3A8B",
            "rgb": [173, 58, 139],
            "alpha": 0.51,
            "cssRgba": "rgba(173, 58, 139, 0.510)"
          }
        },
        {
          "binIndex": 8,
          "label": "27.5-30 dBZ",
          "minDbzInclusive": 27.5,
          "maxDbzExclusive": 30,
          "startDbz": 27.5,
          "belowFilter": false,
          "webColor": {
            "hex": "#A13987",
            "rgb": [161, 57, 135],
            "alpha": 0.555,
            "cssRgba": "rgba(161, 57, 135, 0.555)"
          }
        },
        {
          "binIndex": 9,
          "label": "30-32.5 dBZ",
          "minDbzInclusive": 30,
          "maxDbzExclusive": 32.5,
          "startDbz": 30,
          "belowFilter": false,
          "webColor": {
            "hex": "#953783",
            "rgb": [149, 55, 131],
            "alpha": 0.6,
            "cssRgba": "rgba(149, 55, 131, 0.600)"
          }
        },
        {
          "binIndex": 10,
          "label": "32.5-35 dBZ",
          "minDbzInclusive": 32.5,
          "maxDbzExclusive": 35,
          "startDbz": 32.5,
          "belowFilter": false,
          "webColor": {
            "hex": "#8E3A85",
            "rgb": [142, 58, 133],
            "alpha": 0.645,
            "cssRgba": "rgba(142, 58, 133, 0.645)"
          }
        },
        {
          "binIndex": 11,
          "label": "35-37.5 dBZ",
          "minDbzInclusive": 35,
          "maxDbzExclusive": 37.5,
          "startDbz": 35,
          "belowFilter": false,
          "webColor": {
            "hex": "#883C87",
            "rgb": [136, 60, 135],
            "alpha": 0.69,
            "cssRgba": "rgba(136, 60, 135, 0.690)"
          }
        },
        {
          "binIndex": 12,
          "label": "37.5-40 dBZ",
          "minDbzInclusive": 37.5,
          "maxDbzExclusive": 40,
          "startDbz": 37.5,
          "belowFilter": false,
          "webColor": {
            "hex": "#813F89",
            "rgb": [129, 63, 137],
            "alpha": 0.735,
            "cssRgba": "rgba(129, 63, 137, 0.735)"
          }
        },
        {
          "binIndex": 13,
          "label": "40-42.5 dBZ",
          "minDbzInclusive": 40,
          "maxDbzExclusive": 42.5,
          "startDbz": 40,
          "belowFilter": false,
          "webColor": {
            "hex": "#7A418B",
            "rgb": [122, 65, 139],
            "alpha": 0.78,
            "cssRgba": "rgba(122, 65, 139, 0.780)"
          }
        },
        {
          "binIndex": 14,
          "label": "42.5-45 dBZ",
          "minDbzInclusive": 42.5,
          "maxDbzExclusive": 45,
          "startDbz": 42.5,
          "belowFilter": false,
          "webColor": {
            "hex": "#884C98",
            "rgb": [136, 76, 152],
            "alpha": 0.825,
            "cssRgba": "rgba(136, 76, 152, 0.825)"
          }
        },
        {
          "binIndex": 15,
          "label": "45-47.5 dBZ",
          "minDbzInclusive": 45,
          "maxDbzExclusive": 47.5,
          "startDbz": 45,
          "belowFilter": false,
          "webColor": {
            "hex": "#9657A5",
            "rgb": [150, 87, 165],
            "alpha": 0.87,
            "cssRgba": "rgba(150, 87, 165, 0.870)"
          }
        },
        {
          "binIndex": 16,
          "label": "47.5-50 dBZ",
          "minDbzInclusive": 47.5,
          "maxDbzExclusive": 50,
          "startDbz": 47.5,
          "belowFilter": false,
          "webColor": {
            "hex": "#A462B2",
            "rgb": [164, 98, 178],
            "alpha": 0.915,
            "cssRgba": "rgba(164, 98, 178, 0.915)"
          }
        },
        {
          "binIndex": 17,
          "label": "50-52.5 dBZ",
          "minDbzInclusive": 50,
          "maxDbzExclusive": 52.5,
          "startDbz": 50,
          "belowFilter": false,
          "webColor": {
            "hex": "#B26DBF",
            "rgb": [178, 109, 191],
            "alpha": 0.96,
            "cssRgba": "rgba(178, 109, 191, 0.960)"
          }
        },
        {
          "binIndex": 18,
          "label": "52.5-55 dBZ",
          "minDbzInclusive": 52.5,
          "maxDbzExclusive": 55,
          "startDbz": 52.5,
          "belowFilter": false,
          "webColor": {
            "hex": "#B777C4",
            "rgb": [183, 119, 196],
            "alpha": 1,
            "cssRgba": "rgba(183, 119, 196, 1.000)"
          }
        },
        {
          "binIndex": 19,
          "label": "55-57.5 dBZ",
          "minDbzInclusive": 55,
          "maxDbzExclusive": 57.5,
          "startDbz": 55,
          "belowFilter": false,
          "webColor": {
            "hex": "#BC81C9",
            "rgb": [188, 129, 201],
            "alpha": 1,
            "cssRgba": "rgba(188, 129, 201, 1.000)"
          }
        },
        {
          "binIndex": 20,
          "label": "57.5-60 dBZ",
          "minDbzInclusive": 57.5,
          "maxDbzExclusive": 60,
          "startDbz": 57.5,
          "belowFilter": false,
          "webColor": {
            "hex": "#C18BCE",
            "rgb": [193, 139, 206],
            "alpha": 1,
            "cssRgba": "rgba(193, 139, 206, 1.000)"
          }
        },
        {
          "binIndex": 21,
          "label": "60-62.5 dBZ",
          "minDbzInclusive": 60,
          "maxDbzExclusive": 62.5,
          "startDbz": 60,
          "belowFilter": false,
          "webColor": {
            "hex": "#C695D3",
            "rgb": [198, 149, 211],
            "alpha": 1,
            "cssRgba": "rgba(198, 149, 211, 1.000)"
          }
        },
        {
          "binIndex": 22,
          "label": "62.5-65 dBZ",
          "minDbzInclusive": 62.5,
          "maxDbzExclusive": 65,
          "startDbz": 62.5,
          "belowFilter": false,
          "webColor": {
            "hex": "#CC9FD8",
            "rgb": [204, 159, 216],
            "alpha": 1,
            "cssRgba": "rgba(204, 159, 216, 1.000)"
          }
        },
        {
          "binIndex": 23,
          "label": "65-67.5 dBZ",
          "minDbzInclusive": 65,
          "maxDbzExclusive": 67.5,
          "startDbz": 65,
          "belowFilter": false,
          "webColor": {
            "hex": "#D1A9DD",
            "rgb": [209, 169, 221],
            "alpha": 1,
            "cssRgba": "rgba(209, 169, 221, 1.000)"
          }
        },
        {
          "binIndex": 24,
          "label": "67.5-70 dBZ",
          "minDbzInclusive": 67.5,
          "maxDbzExclusive": 70,
          "startDbz": 67.5,
          "belowFilter": false,
          "webColor": {
            "hex": "#D6B3E2",
            "rgb": [214, 179, 226],
            "alpha": 1,
            "cssRgba": "rgba(214, 179, 226, 1.000)"
          }
        },
        {
          "binIndex": 25,
          "label": "70+ dBZ",
          "minDbzInclusive": 70,
          "maxDbzExclusive": null,
          "startDbz": 70,
          "belowFilter": false,
          "webColor": {
            "hex": "#DBBDE7",
            "rgb": [219, 189, 231],
            "alpha": 1,
            "cssRgba": "rgba(219, 189, 231, 1.000)"
          }
        }
      ]
    },
    "sleet": {
      "displayName": "Sleet",
      "filterDbz": 10,
      "visibleTickLabelsDbz": [10, 20, 30, 40, 50],
      "bins": [
        {
          "binIndex": 0,
          "label": "< 10 dBZ",
          "minDbzInclusive": null,
          "maxDbzExclusive": 10,
          "startDbz": null,
          "belowFilter": true,
          "webColor": {
            "hex": "#000000",
            "rgb": [0, 0, 0],
            "alpha": 0,
            "cssRgba": "rgba(0, 0, 0, 0.000)"
          }
        },
        {
          "binIndex": 1,
          "label": "10-12.5 dBZ",
          "minDbzInclusive": 10,
          "maxDbzExclusive": 12.5,
          "startDbz": 10,
          "belowFilter": false,
          "webColor": {
            "hex": "#CFA84E",
            "rgb": [207, 168, 78],
            "alpha": 0.24,
            "cssRgba": "rgba(207, 168, 78, 0.240)"
          }
        },
        {
          "binIndex": 2,
          "label": "12.5-15 dBZ",
          "minDbzInclusive": 12.5,
          "maxDbzExclusive": 15,
          "startDbz": 12.5,
          "belowFilter": false,
          "webColor": {
            "hex": "#C99E48",
            "rgb": [201, 158, 72],
            "alpha": 0.285,
            "cssRgba": "rgba(201, 158, 72, 0.285)"
          }
        },
        {
          "binIndex": 3,
          "label": "15-17.5 dBZ",
          "minDbzInclusive": 15,
          "maxDbzExclusive": 17.5,
          "startDbz": 15,
          "belowFilter": false,
          "webColor": {
            "hex": "#C49441",
            "rgb": [196, 148, 65],
            "alpha": 0.33,
            "cssRgba": "rgba(196, 148, 65, 0.330)"
          }
        },
        {
          "binIndex": 4,
          "label": "17.5-20 dBZ",
          "minDbzInclusive": 17.5,
          "maxDbzExclusive": 20,
          "startDbz": 17.5,
          "belowFilter": false,
          "webColor": {
            "hex": "#BE8A3B",
            "rgb": [190, 138, 59],
            "alpha": 0.375,
            "cssRgba": "rgba(190, 138, 59, 0.375)"
          }
        },
        {
          "binIndex": 5,
          "label": "20-22.5 dBZ",
          "minDbzInclusive": 20,
          "maxDbzExclusive": 22.5,
          "startDbz": 20,
          "belowFilter": false,
          "webColor": {
            "hex": "#B88034",
            "rgb": [184, 128, 52],
            "alpha": 0.42,
            "cssRgba": "rgba(184, 128, 52, 0.420)"
          }
        },
        {
          "binIndex": 6,
          "label": "22.5-25 dBZ",
          "minDbzInclusive": 22.5,
          "maxDbzExclusive": 25,
          "startDbz": 22.5,
          "belowFilter": false,
          "webColor": {
            "hex": "#B07935",
            "rgb": [176, 121, 53],
            "alpha": 0.465,
            "cssRgba": "rgba(176, 121, 53, 0.465)"
          }
        },
        {
          "binIndex": 7,
          "label": "25-27.5 dBZ",
          "minDbzInclusive": 25,
          "maxDbzExclusive": 27.5,
          "startDbz": 25,
          "belowFilter": false,
          "webColor": {
            "hex": "#A87236",
            "rgb": [168, 114, 54],
            "alpha": 0.51,
            "cssRgba": "rgba(168, 114, 54, 0.510)"
          }
        },
        {
          "binIndex": 8,
          "label": "27.5-30 dBZ",
          "minDbzInclusive": 27.5,
          "maxDbzExclusive": 30,
          "startDbz": 27.5,
          "belowFilter": false,
          "webColor": {
            "hex": "#A06A36",
            "rgb": [160, 106, 54],
            "alpha": 0.555,
            "cssRgba": "rgba(160, 106, 54, 0.555)"
          }
        },
        {
          "binIndex": 9,
          "label": "30-32.5 dBZ",
          "minDbzInclusive": 30,
          "maxDbzExclusive": 32.5,
          "startDbz": 30,
          "belowFilter": false,
          "webColor": {
            "hex": "#986337",
            "rgb": [152, 99, 55],
            "alpha": 0.6,
            "cssRgba": "rgba(152, 99, 55, 0.600)"
          }
        },
        {
          "binIndex": 10,
          "label": "32.5-35 dBZ",
          "minDbzInclusive": 32.5,
          "maxDbzExclusive": 35,
          "startDbz": 32.5,
          "belowFilter": false,
          "webColor": {
            "hex": "#91613B",
            "rgb": [145, 97, 59],
            "alpha": 0.645,
            "cssRgba": "rgba(145, 97, 59, 0.645)"
          }
        },
        {
          "binIndex": 11,
          "label": "35-37.5 dBZ",
          "minDbzInclusive": 35,
          "maxDbzExclusive": 37.5,
          "startDbz": 35,
          "belowFilter": false,
          "webColor": {
            "hex": "#895F3F",
            "rgb": [137, 95, 63],
            "alpha": 0.69,
            "cssRgba": "rgba(137, 95, 63, 0.690)"
          }
        },
        {
          "binIndex": 12,
          "label": "37.5-40 dBZ",
          "minDbzInclusive": 37.5,
          "maxDbzExclusive": 40,
          "startDbz": 37.5,
          "belowFilter": false,
          "webColor": {
            "hex": "#825C43",
            "rgb": [130, 92, 67],
            "alpha": 0.735,
            "cssRgba": "rgba(130, 92, 67, 0.735)"
          }
        },
        {
          "binIndex": 13,
          "label": "40-42.5 dBZ",
          "minDbzInclusive": 40,
          "maxDbzExclusive": 42.5,
          "startDbz": 40,
          "belowFilter": false,
          "webColor": {
            "hex": "#7A5A47",
            "rgb": [122, 90, 71],
            "alpha": 0.78,
            "cssRgba": "rgba(122, 90, 71, 0.780)"
          }
        },
        {
          "binIndex": 14,
          "label": "42.5-45 dBZ",
          "minDbzInclusive": 42.5,
          "maxDbzExclusive": 45,
          "startDbz": 42.5,
          "belowFilter": false,
          "webColor": {
            "hex": "#8A6950",
            "rgb": [138, 105, 80],
            "alpha": 0.825,
            "cssRgba": "rgba(138, 105, 80, 0.825)"
          }
        },
        {
          "binIndex": 15,
          "label": "45-47.5 dBZ",
          "minDbzInclusive": 45,
          "maxDbzExclusive": 47.5,
          "startDbz": 45,
          "belowFilter": false,
          "webColor": {
            "hex": "#997859",
            "rgb": [153, 120, 89],
            "alpha": 0.87,
            "cssRgba": "rgba(153, 120, 89, 0.870)"
          }
        },
        {
          "binIndex": 16,
          "label": "47.5-50 dBZ",
          "minDbzInclusive": 47.5,
          "maxDbzExclusive": 50,
          "startDbz": 47.5,
          "belowFilter": false,
          "webColor": {
            "hex": "#A98662",
            "rgb": [169, 134, 98],
            "alpha": 0.915,
            "cssRgba": "rgba(169, 134, 98, 0.915)"
          }
        },
        {
          "binIndex": 17,
          "label": "50-52.5 dBZ",
          "minDbzInclusive": 50,
          "maxDbzExclusive": 52.5,
          "startDbz": 50,
          "belowFilter": false,
          "webColor": {
            "hex": "#B8956B",
            "rgb": [184, 149, 107],
            "alpha": 0.96,
            "cssRgba": "rgba(184, 149, 107, 0.960)"
          }
        },
        {
          "binIndex": 18,
          "label": "52.5-55 dBZ",
          "minDbzInclusive": 52.5,
          "maxDbzExclusive": 55,
          "startDbz": 52.5,
          "belowFilter": false,
          "webColor": {
            "hex": "#BD9C72",
            "rgb": [189, 156, 114],
            "alpha": 1,
            "cssRgba": "rgba(189, 156, 114, 1.000)"
          }
        },
        {
          "binIndex": 19,
          "label": "55-57.5 dBZ",
          "minDbzInclusive": 55,
          "maxDbzExclusive": 57.5,
          "startDbz": 55,
          "belowFilter": false,
          "webColor": {
            "hex": "#C2A279",
            "rgb": [194, 162, 121],
            "alpha": 1,
            "cssRgba": "rgba(194, 162, 121, 1.000)"
          }
        },
        {
          "binIndex": 20,
          "label": "57.5-60 dBZ",
          "minDbzInclusive": 57.5,
          "maxDbzExclusive": 60,
          "startDbz": 57.5,
          "belowFilter": false,
          "webColor": {
            "hex": "#C7A97F",
            "rgb": [199, 169, 127],
            "alpha": 1,
            "cssRgba": "rgba(199, 169, 127, 1.000)"
          }
        },
        {
          "binIndex": 21,
          "label": "60-62.5 dBZ",
          "minDbzInclusive": 60,
          "maxDbzExclusive": 62.5,
          "startDbz": 60,
          "belowFilter": false,
          "webColor": {
            "hex": "#CCAF86",
            "rgb": [204, 175, 134],
            "alpha": 1,
            "cssRgba": "rgba(204, 175, 134, 1.000)"
          }
        },
        {
          "binIndex": 22,
          "label": "62.5-65 dBZ",
          "minDbzInclusive": 62.5,
          "maxDbzExclusive": 65,
          "startDbz": 62.5,
          "belowFilter": false,
          "webColor": {
            "hex": "#D1B68D",
            "rgb": [209, 182, 141],
            "alpha": 1,
            "cssRgba": "rgba(209, 182, 141, 1.000)"
          }
        },
        {
          "binIndex": 23,
          "label": "65-67.5 dBZ",
          "minDbzInclusive": 65,
          "maxDbzExclusive": 67.5,
          "startDbz": 65,
          "belowFilter": false,
          "webColor": {
            "hex": "#D6BC94",
            "rgb": [214, 188, 148],
            "alpha": 1,
            "cssRgba": "rgba(214, 188, 148, 1.000)"
          }
        },
        {
          "binIndex": 24,
          "label": "67.5-70 dBZ",
          "minDbzInclusive": 67.5,
          "maxDbzExclusive": 70,
          "startDbz": 67.5,
          "belowFilter": false,
          "webColor": {
            "hex": "#DBC39A",
            "rgb": [219, 195, 154],
            "alpha": 1,
            "cssRgba": "rgba(219, 195, 154, 1.000)"
          }
        },
        {
          "binIndex": 25,
          "label": "70+ dBZ",
          "minDbzInclusive": 70,
          "maxDbzExclusive": null,
          "startDbz": 70,
          "belowFilter": false,
          "webColor": {
            "hex": "#E0C9A1",
            "rgb": [224, 201, 161],
            "alpha": 1,
            "cssRgba": "rgba(224, 201, 161, 1.000)"
          }
        }
      ]
    }
  }
}
